odoo/addons/stock_quantity_history_location/README.rst
odoo/addons/stock_quantity_history_location/__init__.py
odoo/addons/stock_quantity_history_location/__manifest__.py
odoo/addons/stock_quantity_history_location/i18n/stock_quantity_history_location.pot
odoo/addons/stock_quantity_history_location/models/__init__.py
odoo/addons/stock_quantity_history_location/models/product.py
odoo/addons/stock_quantity_history_location/readme/CONSTRIBUTORS.rst
odoo/addons/stock_quantity_history_location/readme/DESCRIPTION.rst
odoo/addons/stock_quantity_history_location/readme/USAGE.rst
odoo/addons/stock_quantity_history_location/static/description/icon.png
odoo/addons/stock_quantity_history_location/static/description/index.html
odoo/addons/stock_quantity_history_location/tests/__init__.py
odoo/addons/stock_quantity_history_location/tests/test_stock_quantity_history_location.py
odoo/addons/stock_quantity_history_location/wizards/__init__.py
odoo/addons/stock_quantity_history_location/wizards/stock_quantity_history.py
odoo/addons/stock_quantity_history_location/wizards/stock_quantity_history.xml
odoo11_addon_stock_quantity_history_location-11.0.1.1.0.dist-info/METADATA
odoo11_addon_stock_quantity_history_location-11.0.1.1.0.dist-info/WHEEL
odoo11_addon_stock_quantity_history_location-11.0.1.1.0.dist-info/top_level.txt
odoo11_addon_stock_quantity_history_location-11.0.1.1.0.dist-info/RECORD
